{"id":"cq16I_vNcKLZVSMitladEg","alias":"el-ranchon-santa-clara-3","name":"El Ranchon","image_url":"https:\/\/s3-media2.fl.yelpcdn.com\/bphoto\/hwWQABNzWvz6ai6dhrYxTQ\/o.jpg","is_closed":false,"url":"https:\/\/www.yelp.com\/biz\/el-ranchon-santa-clara-3?adjust_creative=wNVJ2NQ-VXEtJk4AjWcSCg&utm_campaign=yelp_api_v3&utm_medium=api_v3_business_search&utm_source=wNVJ2NQ-VXEtJk4AjWcSCg","review_count":5,"categories":[{"alias":"foodtrucks","title":"Food Trucks"},{"alias":"cuban","title":"Cuban"}],"rating":5.0,"coordinates":{"latitude":37.352097165,"longitude":-121.9737633623},"transactions":[],"location":{"address1":"2608 El Camino Real","address2":null,"address3":"","city":"Santa Clara","zip_code":"95051","country":"US","state":"CA","display_address":["2608 El Camino Real","Santa Clara, CA 95051"]},"phone":"+14088980613","display_phone":"(408) 898-0613","distance":5097.811181529,"business_hours":[{"open":[{"is_overnight":false,"start":"1130","end":"2100","day":1},{"is_overnight":false,"start":"1130","end":"2100","day":2},{"is_overnight":false,"start":"1130","end":"2100","day":3},{"is_overnight":false,"start":"1130","end":"2100","day":4},{"is_overnight":false,"start":"1130","end":"2100","day":5},{"is_overnight":false,"start":"1130","end":"2100","day":6}],"hours_type":"REGULAR","is_open_now":false}],"attributes":{"business_temp_closed":null,"menu_url":"https:\/\/elranchonfood.com\/menu","open24_hours":null,"waitlist_reservation":null},"price":null}
{"id":"68n5oUp_M2HwkJAxiCGjkg","alias":"shubham-halls-sunnyvale","name":"Shubham Halls","image_url":"https:\/\/s3-media2.fl.yelpcdn.com\/bphoto\/ZSLTjyyfzLy2lzwyK98nXA\/o.jpg","is_closed":false,"url":"https:\/\/www.yelp.com\/biz\/shubham-halls-sunnyvale?adjust_creative=wNVJ2NQ-VXEtJk4AjWcSCg&utm_campaign=yelp_api_v3&utm_medium=api_v3_business_search&utm_source=wNVJ2NQ-VXEtJk4AjWcSCg","review_count":6,"categories":[{"alias":"indpak","title":"Indian"}],"rating":5.0,"coordinates":{"latitude":37.3787817495,"longitude":-121.9951654564},"transactions":[],"location":{"address1":"1208 Apollo Way","address2":"Ste 500","address3":null,"city":"Sunnyvale","zip_code":"94085","country":"US","state":"CA","display_address":["1208 Apollo Way","Ste 500","Sunnyvale, CA 94085"]},"phone":"+16693154545","display_phone":"(669) 315-4545","distance":2643.3401448808,"business_hours":[{"open":[{"is_overnight":false,"start":"1100","end":"2300","day":1},{"is_overnight":false,"start":"1100","end":"2300","day":2},{"is_overnight":false,"start":"1100","end":"2300","day":3},{"is_overnight":false,"start":"1100","end":"2300","day":4},{"is_overnight":false,"start":"1100","end":"2300","day":5},{"is_overnight":false,"start":"1100","end":"2300","day":6}],"hours_type":"REGULAR","is_open_now":false}],"attributes":{"business_temp_closed":null,"menu_url":null,"open24_hours":null,"waitlist_reservation":null},"price":null}
{"id":"fg8m-7w18oxV22gElsD40Q","alias":"garretts-bar-and-grill-sunnyvale","name":"Garrett's Bar & Grill","image_url":"https:\/\/s3-media3.fl.yelpcdn.com\/bphoto\/cePMbKgNxav9bhY4DhlvUA\/o.jpg","is_closed":false,"url":"https:\/\/www.yelp.com\/biz\/garretts-bar-and-grill-sunnyvale?adjust_creative=wNVJ2NQ-VXEtJk4AjWcSCg&utm_campaign=yelp_api_v3&utm_medium=api_v3_business_search&utm_source=wNVJ2NQ-VXEtJk4AjWcSCg","review_count":5,"categories":[{"alias":"beerbar","title":"Beer Bar"},{"alias":"tradamerican","title":"American"}],"rating":5.0,"coordinates":{"latitude":37.3961829348,"longitude":-122.0414361151},"transactions":["delivery","pickup"],"location":{"address1":"605 Macara Ave","address2":null,"address3":"","city":"Sunnyvale","zip_code":"94085","country":"US","state":"CA","display_address":["605 Macara Ave","Sunnyvale, CA 94085"]},"phone":"+16692805400","display_phone":"(669) 280-5400","distance":2890.1038873434,"business_hours":[{"open":[{"is_overnight":false,"start":"1100","end":"1900","day":1},{"is_overnight":false,"start":"1100","end":"1900","day":2},{"is_overnight":false,"start":"1100","end":"1900","day":3},{"is_overnight":false,"start":"1100","end":"2300","day":4},{"is_overnight":false,"start":"1100","end":"1900","day":5},{"is_overnight":false,"start":"1100","end":"1900","day":6}],"hours_type":"REGULAR","is_open_now":false}],"attributes":{"business_temp_closed":null,"menu_url":"https:\/\/garrett.bar\/menu\/","open24_hours":null,"waitlist_reservation":null},"price":null}
{"id":"6GskGBzMidpRwiEN9hDRcw","alias":"trade-routes-eateries-sunnyvale-2","name":"Trade Routes Eateries","image_url":"https:\/\/s3-media3.fl.yelpcdn.com\/bphoto\/cyzlm20Wtehp2V-a_Hp4cw\/o.jpg","is_closed":false,"url":"https:\/\/www.yelp.com\/biz\/trade-routes-eateries-sunnyvale-2?adjust_creative=wNVJ2NQ-VXEtJk4AjWcSCg&utm_campaign=yelp_api_v3&utm_medium=api_v3_business_search&utm_source=wNVJ2NQ-VXEtJk4AjWcSCg","review_count":9,"categories":[{"alias":"indpak","title":"Indian"},{"alias":"bangladeshi","title":"Bangladeshi"},{"alias":"malaysian","title":"Malaysian"}],"rating":5.0,"coordinates":{"latitude":37.38311,"longitude":-122.04608},"transactions":["delivery"],"location":{"address1":"1026 W Evelyn Ave","address2":null,"address3":"","city":"Sunnyvale","zip_code":"94086","country":"US","state":"CA","display_address":["1026 W Evelyn Ave","Sunnyvale, CA 94086"]},"phone":"+14087594656","display_phone":"(408) 759-4656","distance":2165.9283138574,"business_hours":[{"open":[{"is_overnight":false,"start":"1100","end":"1400","day":0},{"is_overnight":false,"start":"1600","end":"2000","day":0},{"is_overnight":false,"start":"1100","end":"1400","day":1},{"is_overnight":false,"start":"1600","end":"2000","day":1},{"is_overnight":false,"start":"1100","end":"1400","day":2},{"is_overnight":false,"start":"1600","end":"2000","day":2},{"is_overnight":false,"start":"1100","end":"1400","day":3},{"is_overnight":false,"start":"1600","end":"2000","day":3},{"is_overnight":false,"start":"1100","end":"1400","day":4},{"is_overnight":false,"start":"1700","end":"2000","day":4},{"is_overnight":false,"start":"1600","end":"2000","day":6}],"hours_type":"REGULAR","is_open_now":false}],"attributes":{"business_temp_closed":1751353200,"menu_url":null,"open24_hours":null,"waitlist_reservation":null},"price":null}
{"id":"8W_HyIevELguoBjQcPTO8w","alias":"palmita-sunnyvale","name":"Palmita","image_url":"https:\/\/s3-media4.fl.yelpcdn.com\/bphoto\/wwhTFVKr3bOAfwFGOmJfuw\/o.jpg","is_closed":false,"url":"https:\/\/www.yelp.com\/biz\/palmita-sunnyvale?adjust_creative=wNVJ2NQ-VXEtJk4AjWcSCg&utm_campaign=yelp_api_v3&utm_medium=api_v3_business_search&utm_source=wNVJ2NQ-VXEtJk4AjWcSCg","review_count":5,"categories":[{"alias":"mexican","title":"Mexican"},{"alias":"salad","title":"Salad"},{"alias":"fooddeliveryservices","title":"Food Delivery Services"}],"rating":5.0,"coordinates":{"latitude":37.3831097925,"longitude":-122.0460806},"transactions":["delivery","pickup"],"location":{"address1":"1026 W Evelyn Ave","address2":null,"address3":"","city":"Sunnyvale","zip_code":"94086","country":"US","state":"CA","display_address":["1026 W Evelyn Ave","Sunnyvale, CA 94086"]},"phone":"","display_phone":"","distance":2164.1352191918,"business_hours":[{"open":[{"is_overnight":false,"start":"0930","end":"2300","day":0},{"is_overnight":false,"start":"0930","end":"2300","day":1},{"is_overnight":false,"start":"0930","end":"2300","day":2},{"is_overnight":false,"start":"0930","end":"2300","day":3},{"is_overnight":false,"start":"0930","end":"2300","day":4},{"is_overnight":false,"start":"1030","end":"2300","day":5},{"is_overnight":false,"start":"1030","end":"2300","day":6}],"hours_type":"REGULAR","is_open_now":true}],"attributes":{"business_temp_closed":null,"menu_url":"https:\/\/www.eatpalmita.com\/menu","open24_hours":null,"waitlist_reservation":false},"price":null}
{"id":"s6uo048pkp1iFwGgZ2xLVw","alias":"nalapaka-sunnyvale","name":"Nalapaka","image_url":"https:\/\/s3-media2.fl.yelpcdn.com\/bphoto\/68Uq2RYcVje4SwVe_ADrsg\/o.jpg","is_closed":false,"url":"https:\/\/www.yelp.com\/biz\/nalapaka-sunnyvale?adjust_creative=wNVJ2NQ-VXEtJk4AjWcSCg&utm_campaign=yelp_api_v3&utm_medium=api_v3_business_search&utm_source=wNVJ2NQ-VXEtJk4AjWcSCg","review_count":26,"categories":[{"alias":"indpak","title":"Indian"}],"rating":5.0,"coordinates":{"latitude":37.38311,"longitude":-122.04608},"transactions":["delivery"],"location":{"address1":"1026 W Evelyn Ave","address2":null,"address3":"","city":"Sunnyvale","zip_code":"94086","country":"US","state":"CA","display_address":["1026 W Evelyn Ave","Sunnyvale, CA 94086"]},"phone":"+15105165015","display_phone":"(510) 516-5015","distance":2165.9283138574,"business_hours":[{"open":[{"is_overnight":false,"start":"1030","end":"2130","day":1},{"is_overnight":false,"start":"1030","end":"2130","day":2},{"is_overnight":false,"start":"1030","end":"2130","day":3},{"is_overnight":false,"start":"1030","end":"2200","day":4},{"is_overnight":false,"start":"1030","end":"2200","day":5},{"is_overnight":false,"start":"1030","end":"1600","day":6}],"hours_type":"REGULAR","is_open_now":false}],"attributes":{"business_temp_closed":null,"menu_url":"https:\/\/www.nalapaka.com\/menu","open24_hours":null,"waitlist_reservation":null},"price":null}
{"id":"f4WbJSS_DIzrcUT-7Pnc0A","alias":"dl-brazuca-sunnyvale-2","name":"DL Brazuca","image_url":"https:\/\/s3-media2.fl.yelpcdn.com\/bphoto\/bMWwXIVJSpmpmysLkmIAYA\/o.jpg","is_closed":false,"url":"https:\/\/www.yelp.com\/biz\/dl-brazuca-sunnyvale-2?adjust_creative=wNVJ2NQ-VXEtJk4AjWcSCg&utm_campaign=yelp_api_v3&utm_medium=api_v3_business_search&utm_source=wNVJ2NQ-VXEtJk4AjWcSCg","review_count":41,"categories":[{"alias":"brazilian","title":"Brazilian"}],"rating":4.9,"coordinates":{"latitude":37.3825090393,"longitude":-121.994861414},"transactions":["delivery","pickup"],"location":{"address1":"510 Lawrence Expu","address2":"Ste 101","address3":"","city":"Sunnyvale","zip_code":"94085","country":"US","state":"CA","display_address":["510 Lawrence Expu","Ste 101","Sunnyvale, CA 94085"]},"phone":"+14088368056","display_phone":"(408) 836-8056","distance":2782.512618275,"business_hours":[{"open":[{"is_overnight":false,"start":"0900","end":"1700","day":0},{"is_overnight":false,"start":"0900","end":"1700","day":1},{"is_overnight":false,"start":"0900","end":"1700","day":2},{"is_overnight":false,"start":"0900","end":"1700","day":3},{"is_overnight":false,"start":"0900","end":"1700","day":4},{"is_overnight":false,"start":"0900","end":"1400","day":5}],"hours_type":"REGULAR","is_open_now":false}],"attributes":{"business_temp_closed":null,"menu_url":null,"open24_hours":null,"waitlist_reservation":null},"price":null}
{"id":"E1SYZ1JoavNCpYxU7bvRWA","alias":"quick-dog-campbell","name":"Quick Dog","image_url":"https:\/\/s3-media2.fl.yelpcdn.com\/bphoto\/9FSJ8dhrE0LwRCIswhxPrQ\/o.jpg","is_closed":false,"url":"https:\/\/www.yelp.com\/biz\/quick-dog-campbell?adjust_creative=wNVJ2NQ-VXEtJk4AjWcSCg&utm_campaign=yelp_api_v3&utm_medium=api_v3_business_search&utm_source=wNVJ2NQ-VXEtJk4AjWcSCg","review_count":43,"categories":[{"alias":"hotdog","title":"Hot Dogs"},{"alias":"streetvendors","title":"Street Vendors"}],"rating":4.9,"coordinates":{"latitude":37.29413,"longitude":-121.95864},"transactions":[],"location":{"address1":"","address2":null,"address3":"","city":"Campbell","zip_code":"95051","country":"US","state":"CA","display_address":["Campbell, CA 95051"]},"phone":"+14083915038","display_phone":"(408) 391-5038","distance":4114.3906846212,"business_hours":[],"attributes":{"business_temp_closed":null,"menu_url":"http:\/\/quickdogcatering.com\/menu","open24_hours":null,"waitlist_reservation":null},"price":"$"}
{"id":"D2INKZxXi6eIFA4yY5yjhQ","alias":"el-ranchero-del-sur-sunnyvale","name":"El Ranchero Del Sur","image_url":"https:\/\/s3-media1.fl.yelpcdn.com\/bphoto\/m9ecZQkc6d8xuWXpsx5TRQ\/o.jpg","is_closed":false,"url":"https:\/\/www.yelp.com\/biz\/el-ranchero-del-sur-sunnyvale?adjust_creative=wNVJ2NQ-VXEtJk4AjWcSCg&utm_campaign=yelp_api_v3&utm_medium=api_v3_business_search&utm_source=wNVJ2NQ-VXEtJk4AjWcSCg","review_count":13,"categories":[{"alias":"mexican","title":"Mexican"},{"alias":"foodtrucks","title":"Food Trucks"}],"rating":4.8,"coordinates":{"latitude":37.353058,"longitude":-122.004338},"transactions":[],"location":{"address1":"1053 E El Camino Real","address2":null,"address3":"","city":"Sunnyvale","zip_code":"94087","country":"US","state":"CA","display_address":["1053 E El Camino Real","Sunnyvale, CA 94087"]},"phone":"+14088991419","display_phone":"(408) 899-1419","distance":2927.8905092323,"business_hours":[{"open":[{"is_overnight":false,"start":"1000","end":"2000","day":0},{"is_overnight":false,"start":"1000","end":"2000","day":1},{"is_overnight":false,"start":"1000","end":"2000","day":2},{"is_overnight":false,"start":"1000","end":"2000","day":3},{"is_overnight":false,"start":"1000","end":"2000","day":4}],"hours_type":"REGULAR","is_open_now":false}],"attributes":{"business_temp_closed":null,"menu_url":null,"open24_hours":null,"waitlist_reservation":null},"price":null}
{"id":"5fRA208ZZUybxc_6hK5uNA","alias":"lindas-taqueria-sunnyvale-ca","name":"Lindas Taqueria","image_url":"https:\/\/s3-media1.fl.yelpcdn.com\/bphoto\/w6ZDy41EDNGoBZbHuNJyaQ\/o.jpg","is_closed":false,"url":"https:\/\/www.yelp.com\/biz\/lindas-taqueria-sunnyvale-ca?adjust_creative=wNVJ2NQ-VXEtJk4AjWcSCg&utm_campaign=yelp_api_v3&utm_medium=api_v3_business_search&utm_source=wNVJ2NQ-VXEtJk4AjWcSCg","review_count":39,"categories":[{"alias":"foodtrucks","title":"Food Trucks"},{"alias":"tacos","title":"Tacos"}],"rating":4.8,"coordinates":{"latitude":37.413716115,"longitude":-122.0211487411},"transactions":[],"location":{"address1":"1322 Bordeaux Dr","address2":null,"address3":null,"city":"Sunnyvale Ca","zip_code":"95051","country":"US","state":"CA","display_address":["1322 Bordeaux Dr","Sunnyvale Ca, CA 95051"]},"phone":"+14087018698","display_phone":"(408) 701-8698","distance":4429.6954940467,"business_hours":[{"open":[{"is_overnight":false,"start":"0900","end":"1300","day":0},{"is_overnight":false,"start":"0900","end":"1300","day":1},{"is_overnight":false,"start":"0900","end":"1300","day":2},{"is_overnight":false,"start":"0900","end":"1300","day":3},{"is_overnight":false,"start":"0900","end":"1300","day":4}],"hours_type":"REGULAR","is_open_now":false}],"attributes":{"business_temp_closed":null,"menu_url":null,"open24_hours":null,"waitlist_reservation":null},"price":null}
{"id":"oa61UxyQ0ssQ7a8s6AJUag","alias":"feng-hotpot-sunnyvale-2","name":"Feng Hotpot","image_url":"https:\/\/s3-media3.fl.yelpcdn.com\/bphoto\/YCA8S660l8JUtcktpVMtAA\/o.jpg","is_closed":false,"url":"https:\/\/www.yelp.com\/biz\/feng-hotpot-sunnyvale-2?adjust_creative=wNVJ2NQ-VXEtJk4AjWcSCg&utm_campaign=yelp_api_v3&utm_medium=api_v3_business_search&utm_source=wNVJ2NQ-VXEtJk4AjWcSCg","review_count":112,"categories":[{"alias":"hotpot","title":"Hot Pot"}],"rating":4.8,"coordinates":{"latitude":37.338746,"longitude":-122.042587},"transactions":["restaurant_reservation"],"location":{"address1":"1669 Hollenbeck Ave","address2":"Ste A","address3":"","city":"Sunnyvale","zip_code":"94087","country":"US","state":"CA","display_address":["1669 Hollenbeck Ave","Ste A","Sunnyvale, CA 94087"]},"phone":"+14082124129","display_phone":"(408) 212-4129","distance":4232.3459446784,"business_hours":[{"open":[{"is_overnight":false,"start":"1130","end":"1400","day":0},{"is_overnight":false,"start":"1700","end":"2130","day":0},{"is_overnight":false,"start":"1130","end":"1400","day":1},{"is_overnight":false,"start":"1700","end":"2130","day":1},{"is_overnight":false,"start":"1130","end":"1400","day":2},{"is_overnight":false,"start":"1700","end":"2130","day":2},{"is_overnight":false,"start":"1130","end":"1400","day":3},{"is_overnight":false,"start":"1700","end":"2130","day":3},{"is_overnight":false,"start":"1130","end":"1400","day":4},{"is_overnight":false,"start":"1700","end":"2130","day":4},{"is_overnight":false,"start":"1130","end":"1430","day":5},{"is_overnight":false,"start":"1700","end":"2130","day":5},{"is_overnight":false,"start":"1130","end":"1430","day":6},{"is_overnight":false,"start":"1700","end":"2130","day":6}],"hours_type":"REGULAR","is_open_now":true}],"attributes":{"business_temp_closed":null,"menu_url":null,"open24_hours":null,"waitlist_reservation":true},"price":null}
{"id":"DhgRp6ICkLV-BTqXPjth9Q","alias":"tandoori-pizza-sunnyvale-2","name":"Tandoori Pizza","image_url":"https:\/\/s3-media1.fl.yelpcdn.com\/bphoto\/Xb7DopS9WIpt6Hm9n9U_GQ\/o.jpg","is_closed":false,"url":"https:\/\/www.yelp.com\/biz\/tandoori-pizza-sunnyvale-2?adjust_creative=wNVJ2NQ-VXEtJk4AjWcSCg&utm_campaign=yelp_api_v3&utm_medium=api_v3_business_search&utm_source=wNVJ2NQ-VXEtJk4AjWcSCg","review_count":16,"categories":[{"alias":"pizza","title":"Pizza"},{"alias":"indpak","title":"Indian"},{"alias":"chicken_wings","title":"Chicken Wings"}],"rating":4.8,"coordinates":{"latitude":37.3389000428,"longitude":-122.0426148},"transactions":[],"location":{"address1":"1663 Hollenbeck Ave","address2":null,"address3":"","city":"Sunnyvale","zip_code":"94087","country":"US","state":"CA","display_address":["1663 Hollenbeck Ave","Sunnyvale, CA 94087"]},"phone":"+14088545500","display_phone":"(408) 854-5500","distance":4216.4100655254,"business_hours":[{"open":[{"is_overnight":true,"start":"1000","end":"0200","day":0},{"is_overnight":true,"start":"1000","end":"0200","day":1},{"is_overnight":true,"start":"1000","end":"0200","day":2},{"is_overnight":true,"start":"1000","end":"0200","day":3},{"is_overnight":true,"start":"1000","end":"0200","day":4},{"is_overnight":true,"start":"1000","end":"0200","day":5},{"is_overnight":true,"start":"1000","end":"0200","day":6}],"hours_type":"REGULAR","is_open_now":true}],"attributes":{"business_temp_closed":null,"menu_url":"https:\/\/tandooripizza.com\/menu\/","open24_hours":null,"waitlist_reservation":null},"price":null}
{"id":"AqI7rtuNgfwjU5C06iq_Og","alias":"andys-delicious-dogs-sunnyvale","name":"Andy's Delicious Dogs","image_url":"https:\/\/s3-media3.fl.yelpcdn.com\/bphoto\/q41CbzD0cIySYsM9jdWDuA\/o.jpg","is_closed":false,"url":"https:\/\/www.yelp.com\/biz\/andys-delicious-dogs-sunnyvale?adjust_creative=wNVJ2NQ-VXEtJk4AjWcSCg&utm_campaign=yelp_api_v3&utm_medium=api_v3_business_search&utm_source=wNVJ2NQ-VXEtJk4AjWcSCg","review_count":16,"categories":[{"alias":"streetvendors","title":"Street Vendors"},{"alias":"hotdog","title":"Hot Dogs"}],"rating":4.8,"coordinates":{"latitude":37.3897209167,"longitude":-122.0164413452},"transactions":[],"location":{"address1":"","address2":"","address3":"","city":"Sunnyvale","zip_code":"94085","country":"US","state":"CA","display_address":["Sunnyvale, CA 94085"]},"phone":"+14082196922","display_phone":"(408) 219-6922","distance":1811.7814345642,"business_hours":[{"open":[{"is_overnight":false,"start":"1030","end":"1630","day":2},{"is_overnight":false,"start":"1030","end":"1630","day":3},{"is_overnight":false,"start":"1030","end":"1630","day":4},{"is_overnight":false,"start":"1030","end":"1630","day":5},{"is_overnight":false,"start":"1030","end":"1630","day":6}],"hours_type":"REGULAR","is_open_now":false}],"attributes":{"business_temp_closed":null,"menu_url":null,"open24_hours":null,"waitlist_reservation":null},"price":null}
{"id":"Ua7Fj3Yx9iDpIzh9RHSLww","alias":"tacos-la-guerita-sunnyvale","name":"Tacos La Guerita","image_url":"https:\/\/s3-media3.fl.yelpcdn.com\/bphoto\/Cqxj9QXZZh3i4jqFjr2jiw\/o.jpg","is_closed":false,"url":"https:\/\/www.yelp.com\/biz\/tacos-la-guerita-sunnyvale?adjust_creative=wNVJ2NQ-VXEtJk4AjWcSCg&utm_campaign=yelp_api_v3&utm_medium=api_v3_business_search&utm_source=wNVJ2NQ-VXEtJk4AjWcSCg","review_count":37,"categories":[{"alias":"mexican","title":"Mexican"},{"alias":"foodtrucks","title":"Food Trucks"}],"rating":4.8,"coordinates":{"latitude":37.39134,"longitude":-122.01353},"transactions":[],"location":{"address1":"617 Caliente Dr","address2":null,"address3":null,"city":"Sunnyvale","zip_code":"94085","country":"US","state":"CA","display_address":["617 Caliente Dr","Sunnyvale, CA 94085"]},"phone":"+14085697229","display_phone":"(408) 569-7229","distance":2170.0643762433,"business_hours":[{"open":[{"is_overnight":false,"start":"1100","end":"2100","day":0},{"is_overnight":false,"start":"1100","end":"2100","day":1},{"is_overnight":false,"start":"1100","end":"2100","day":2},{"is_overnight":false,"start":"1100","end":"2100","day":3},{"is_overnight":false,"start":"1100","end":"2100","day":4},{"is_overnight":false,"start":"1100","end":"1900","day":5}],"hours_type":"REGULAR","is_open_now":false}],"attributes":{"business_temp_closed":null,"menu_url":"","open24_hours":null,"waitlist_reservation":null},"price":null}
{"id":"nwVkEynM9AaNT5ALL_KNpQ","alias":"bombay-express-sunnyvale","name":"Bombay Express","image_url":"https:\/\/s3-media2.fl.yelpcdn.com\/bphoto\/d4h1SuV-V3SGG73mzzsaow\/o.jpg","is_closed":false,"url":"https:\/\/www.yelp.com\/biz\/bombay-express-sunnyvale?adjust_creative=wNVJ2NQ-VXEtJk4AjWcSCg&utm_campaign=yelp_api_v3&utm_medium=api_v3_business_search&utm_source=wNVJ2NQ-VXEtJk4AjWcSCg","review_count":5,"categories":[{"alias":"desserts","title":"Desserts"},{"alias":"indpak","title":"Indian"},{"alias":"burgers","title":"Burgers"}],"rating":4.8,"coordinates":{"latitude":37.3523992119,"longitude":-122.0031038},"transactions":[],"location":{"address1":"1073 E El Camino Real","address2":"Ste 1","address3":"","city":"Sunnyvale","zip_code":"94087","country":"US","state":"CA","display_address":["1073 E El Camino Real","Ste 1","Sunnyvale, CA 94087"]},"phone":"+16012782940","display_phone":"(601) 278-2940","distance":3051.747066602,"business_hours":[{"open":[{"is_overnight":false,"start":"0800","end":"1200","day":0},{"is_overnight":false,"start":"1700","end":"2200","day":0},{"is_overnight":false,"start":"0800","end":"1200","day":1},{"is_overnight":false,"start":"1700","end":"2200","day":1},{"is_overnight":false,"start":"0800","end":"1200","day":2},{"is_overnight":false,"start":"1700","end":"2200","day":2},{"is_overnight":false,"start":"0800","end":"1200","day":3},{"is_overnight":false,"start":"1700","end":"2200","day":3},{"is_overnight":false,"start":"0800","end":"1200","day":4},{"is_overnight":false,"start":"1700","end":"2300","day":4},{"is_overnight":false,"start":"0800","end":"1200","day":5},{"is_overnight":false,"start":"1700","end":"2300","day":5},{"is_overnight":false,"start":"1200","end":"2200","day":6}],"hours_type":"REGULAR","is_open_now":true}],"attributes":{"business_temp_closed":null,"menu_url":"https:\/\/online-ordering.innowi.com\/branch\/bombayexpress","open24_hours":null,"waitlist_reservation":null},"price":null}
{"id":"DBDbaXmAN4oBOZ7Zv12ZGw","alias":"chai-pe-charcha-sunnyvale","name":"Chai Pe Charcha","image_url":"https:\/\/s3-media2.fl.yelpcdn.com\/bphoto\/3PRVmKjz-jC7APHh9_H2EA\/o.jpg","is_closed":false,"url":"https:\/\/www.yelp.com\/biz\/chai-pe-charcha-sunnyvale?adjust_creative=wNVJ2NQ-VXEtJk4AjWcSCg&utm_campaign=yelp_api_v3&utm_medium=api_v3_business_search&utm_source=wNVJ2NQ-VXEtJk4AjWcSCg","review_count":9,"categories":[{"alias":"foodtrucks","title":"Food Trucks"},{"alias":"indpak","title":"Indian"},{"alias":"sandwiches","title":"Sandwiches"}],"rating":4.8,"coordinates":{"latitude":37.3752952953,"longitude":-122.0582463562},"transactions":[],"location":{"address1":"1255 El Camino Real","address2":null,"address3":"","city":"Sunnyvale","zip_code":"94087","country":"US","state":"CA","display_address":["1255 El Camino Real","Sunnyvale, CA 94087"]},"phone":"+16509060184","display_phone":"(650) 906-0184","distance":2989.1923146292,"business_hours":[],"attributes":{"business_temp_closed":null,"menu_url":null,"open24_hours":null,"waitlist_reservation":null},"price":null}
{"id":"2h-XMOG6NLdjmyO1BsMHPg","alias":"lhl-malatang-sunnyvale","name":"LHL Malatang","image_url":"https:\/\/s3-media4.fl.yelpcdn.com\/bphoto\/E0pFYxM21uNCVYywYryF5g\/o.jpg","is_closed":false,"url":"https:\/\/www.yelp.com\/biz\/lhl-malatang-sunnyvale?adjust_creative=wNVJ2NQ-VXEtJk4AjWcSCg&utm_campaign=yelp_api_v3&utm_medium=api_v3_business_search&utm_source=wNVJ2NQ-VXEtJk4AjWcSCg","review_count":9,"categories":[{"alias":"chinese","title":"Chinese"},{"alias":"buffets","title":"Buffets"}],"rating":4.8,"coordinates":{"latitude":37.33898,"longitude":-122.04258},"transactions":[],"location":{"address1":"1661 Hollenbeck Ave","address2":"","address3":null,"city":"Sunnyvale","zip_code":"94087","country":"US","state":"CA","display_address":["1661 Hollenbeck Ave","Sunnyvale, CA 94087"]},"phone":"","display_phone":"","distance":4207.0370204748,"business_hours":[],"attributes":{"business_temp_closed":null,"menu_url":null,"open24_hours":null,"waitlist_reservation":null},"price":null}
{"id":"-YV2Mp3oHj0b-DDvYxrsOA","alias":"el-sabroson-de-la-linea-2-santa-clara","name":"El Sabroson De La Linea 2","image_url":"https:\/\/s3-media2.fl.yelpcdn.com\/bphoto\/0iiJ4Z74qSTq37rrXMsflw\/o.jpg","is_closed":false,"url":"https:\/\/www.yelp.com\/biz\/el-sabroson-de-la-linea-2-santa-clara?adjust_creative=wNVJ2NQ-VXEtJk4AjWcSCg&utm_campaign=yelp_api_v3&utm_medium=api_v3_business_search&utm_source=wNVJ2NQ-VXEtJk4AjWcSCg","review_count":47,"categories":[{"alias":"foodtrucks","title":"Food Trucks"},{"alias":"mexican","title":"Mexican"}],"rating":4.8,"coordinates":{"latitude":37.3745702121,"longitude":-121.9801012485},"transactions":[],"location":{"address1":"2945 Oakmead Village Ct","address2":null,"address3":"","city":"Santa Clara","zip_code":"95051","country":"US","state":"CA","display_address":["2945 Oakmead Village Ct","Santa Clara, CA 95051"]},"phone":"+14089913794","display_phone":"(408) 991-3794","distance":3920.3273398577,"business_hours":[{"open":[{"is_overnight":false,"start":"0830","end":"1500","day":0},{"is_overnight":false,"start":"0830","end":"1500","day":1},{"is_overnight":false,"start":"0830","end":"1500","day":2},{"is_overnight":false,"start":"0830","end":"1500","day":3},{"is_overnight":false,"start":"0830","end":"1500","day":4}],"hours_type":"REGULAR","is_open_now":false}],"attributes":{"business_temp_closed":null,"menu_url":null,"open24_hours":null,"waitlist_reservation":null},"price":"$"}
{"id":"AaRJaL_i6MVxwcsOVTPEIw","alias":"san-miguel-taqueria-mountain-view","name":"San Miguel Taqueria","image_url":"https:\/\/s3-media2.fl.yelpcdn.com\/bphoto\/LyhezHRqYeRwHzwBuzSbxg\/o.jpg","is_closed":false,"url":"https:\/\/www.yelp.com\/biz\/san-miguel-taqueria-mountain-view?adjust_creative=wNVJ2NQ-VXEtJk4AjWcSCg&utm_campaign=yelp_api_v3&utm_medium=api_v3_business_search&utm_source=wNVJ2NQ-VXEtJk4AjWcSCg","review_count":17,"categories":[{"alias":"tacos","title":"Tacos"}],"rating":4.8,"coordinates":{"latitude":37.38055,"longitude":-122.07491},"transactions":[],"location":{"address1":"975 Bay St","address2":null,"address3":"","city":"Mountain View","zip_code":"94040","country":"US","state":"CA","display_address":["975 Bay St","Mountain View, CA 94040"]},"phone":"+14083340152","display_phone":"(408) 334-0152","distance":4515.6661477654,"business_hours":[{"open":[{"is_overnight":false,"start":"1000","end":"2100","day":0},{"is_overnight":false,"start":"1000","end":"2100","day":1},{"is_overnight":false,"start":"1000","end":"2100","day":2},{"is_overnight":false,"start":"1000","end":"2100","day":3},{"is_overnight":false,"start":"1000","end":"2100","day":4},{"is_overnight":false,"start":"1000","end":"1900","day":5}],"hours_type":"REGULAR","is_open_now":false}],"attributes":{"business_temp_closed":null,"menu_url":null,"open24_hours":null,"waitlist_reservation":null},"price":null}
{"id":"fDA6e7EzNGzwjKA9sFEpHA","alias":"chaat-on-wheels-sunnyvale","name":"Chaat on Wheels","image_url":"https:\/\/s3-media1.fl.yelpcdn.com\/bphoto\/c-VKzRWOSmBO2YofSiQ-Yg\/o.jpg","is_closed":false,"url":"https:\/\/www.yelp.com\/biz\/chaat-on-wheels-sunnyvale?adjust_creative=wNVJ2NQ-VXEtJk4AjWcSCg&utm_campaign=yelp_api_v3&utm_medium=api_v3_business_search&utm_source=wNVJ2NQ-VXEtJk4AjWcSCg","review_count":86,"categories":[{"alias":"indpak","title":"Indian"},{"alias":"foodtrucks","title":"Food Trucks"}],"rating":4.8,"coordinates":{"latitude":37.3963652612,"longitude":-121.996206},"transactions":[],"location":{"address1":"1101 Lawrence Expy","address2":null,"address3":"","city":"Sunnyvale","zip_code":"94089","country":"US","state":"CA","display_address":["1101 Lawrence Expy","Sunnyvale, CA 94089"]},"phone":"+16696498039","display_phone":"(669) 649-8039","distance":3526.3387267473,"business_hours":[{"open":[{"is_overnight":false,"start":"1100","end":"2100","day":0},{"is_overnight":false,"start":"1100","end":"2100","day":1},{"is_overnight":false,"start":"1100","end":"2100","day":2},{"is_overnight":false,"start":"1100","end":"2100","day":3},{"is_overnight":false,"start":"1100","end":"2100","day":4},{"is_overnight":false,"start":"1100","end":"2100","day":5},{"is_overnight":false,"start":"1100","end":"2100","day":6}],"hours_type":"REGULAR","is_open_now":false}],"attributes":{"business_temp_closed":null,"menu_url":null,"open24_hours":null,"waitlist_reservation":null},"price":null}
{"id":"R0Xn_A6lL7D8M7Xni9iKRQ","alias":"madhu-idiyappa-kadai-santa-clara","name":"Madhu Idiyappa Kadai","image_url":"https:\/\/s3-media2.fl.yelpcdn.com\/bphoto\/6bgav8d6BxgK-Hde8jrNWg\/o.jpg","is_closed":false,"url":"https:\/\/www.yelp.com\/biz\/madhu-idiyappa-kadai-santa-clara?adjust_creative=wNVJ2NQ-VXEtJk4AjWcSCg&utm_campaign=yelp_api_v3&utm_medium=api_v3_business_search&utm_source=wNVJ2NQ-VXEtJk4AjWcSCg","review_count":32,"categories":[{"alias":"foodtrucks","title":"Food Trucks"},{"alias":"indpak","title":"Indian"}],"rating":4.8,"coordinates":{"latitude":37.3526045658,"longitude":-121.9987836444},"transactions":["delivery","pickup"],"location":{"address1":"3725 El Camino Real","address2":null,"address3":"","city":"Santa Clara","zip_code":"95051","country":"US","state":"CA","display_address":["3725 El Camino Real","Santa Clara, CA 95051"]},"phone":"+14082101196","display_phone":"(408) 210-1196","distance":3284.9929840834,"business_hours":[{"open":[{"is_overnight":false,"start":"0830","end":"1430","day":0},{"is_overnight":false,"start":"1700","end":"2200","day":0},{"is_overnight":false,"start":"0830","end":"1430","day":2},{"is_overnight":false,"start":"1700","end":"2200","day":2},{"is_overnight":false,"start":"0830","end":"1430","day":3},{"is_overnight":false,"start":"1700","end":"2200","day":3},{"is_overnight":false,"start":"0830","end":"1430","day":4},{"is_overnight":false,"start":"1700","end":"2230","day":4},{"is_overnight":false,"start":"0830","end":"1430","day":5},{"is_overnight":false,"start":"1700","end":"2230","day":5},{"is_overnight":false,"start":"0830","end":"1430","day":6},{"is_overnight":false,"start":"1700","end":"2200","day":6}],"hours_type":"REGULAR","is_open_now":true}],"attributes":{"business_temp_closed":null,"menu_url":null,"open24_hours":null,"waitlist_reservation":null},"price":null}
{"id":"FfboajTuailTSFiv7-FWWw","alias":"chachos-tacos-sunnyvale","name":"Chachos Tacos","image_url":"https:\/\/s3-media4.fl.yelpcdn.com\/bphoto\/dwzHb1LYWz7dmUdnDqzcIQ\/o.jpg","is_closed":false,"url":"https:\/\/www.yelp.com\/biz\/chachos-tacos-sunnyvale?adjust_creative=wNVJ2NQ-VXEtJk4AjWcSCg&utm_campaign=yelp_api_v3&utm_medium=api_v3_business_search&utm_source=wNVJ2NQ-VXEtJk4AjWcSCg","review_count":4,"categories":[{"alias":"tacos","title":"Tacos"},{"alias":"foodstands","title":"Food Stands"}],"rating":5.0,"coordinates":{"latitude":37.371691,"longitude":-122.023127},"transactions":[],"location":{"address1":null,"address2":null,"address3":null,"city":"Sunnyvale","zip_code":"94086","country":"US","state":"CA","display_address":["Sunnyvale, CA 94086"]},"phone":"+16504766857","display_phone":"(650) 476-6857","distance":279.023470429,"business_hours":[{"open":[{"is_overnight":false,"start":"0830","end":"2000","day":0},{"is_overnight":false,"start":"0830","end":"2000","day":1},{"is_overnight":false,"start":"0830","end":"2000","day":2},{"is_overnight":false,"start":"0830","end":"2000","day":3},{"is_overnight":false,"start":"0830","end":"2000","day":4},{"is_overnight":false,"start":"0830","end":"2000","day":5},{"is_overnight":false,"start":"0830","end":"2000","day":6}],"hours_type":"REGULAR","is_open_now":false}],"attributes":{"business_temp_closed":null,"menu_url":null,"open24_hours":null,"waitlist_reservation":false},"price":null}
{"id":"TVBTGVDabVk9i8VIWT_Hrg","alias":"bikanervala-sunnyvale","name":"Bikanervala","image_url":"https:\/\/s3-media4.fl.yelpcdn.com\/bphoto\/Q9lq6HPDARHBALGJ5ZX35w\/o.jpg","is_closed":false,"url":"https:\/\/www.yelp.com\/biz\/bikanervala-sunnyvale?adjust_creative=wNVJ2NQ-VXEtJk4AjWcSCg&utm_campaign=yelp_api_v3&utm_medium=api_v3_business_search&utm_source=wNVJ2NQ-VXEtJk4AjWcSCg","review_count":4,"categories":[{"alias":"indpak","title":"Indian"}],"rating":5.0,"coordinates":{"latitude":37.3675,"longitude":-121.99773},"transactions":[],"location":{"address1":"1155 Reed Ave","address2":"Ste A","address3":"","city":"Sunnyvale","zip_code":"94086","country":"US","state":"CA","display_address":["1155 Reed Ave","Ste A","Sunnyvale, CA 94086"]},"phone":"+19252168888","display_phone":"(925) 216-8888","distance":2478.0285466186,"business_hours":[{"open":[{"is_overnight":false,"start":"1600","end":"2000","day":0},{"is_overnight":false,"start":"1600","end":"2000","day":1},{"is_overnight":false,"start":"1600","end":"2000","day":2},{"is_overnight":false,"start":"1600","end":"2000","day":3},{"is_overnight":false,"start":"1200","end":"2000","day":4},{"is_overnight":false,"start":"1000","end":"2000","day":5},{"is_overnight":false,"start":"1000","end":"2000","day":6}],"hours_type":"REGULAR","is_open_now":false}],"attributes":{"business_temp_closed":1748761200,"menu_url":null,"open24_hours":null,"waitlist_reservation":null},"price":null}
{"id":"9ALFSNsRUfmBtFAqYXEG9w","alias":"mangal-turkish-grill-sunnyvale","name":"Mangal Turkish Grill","image_url":"https:\/\/s3-media2.fl.yelpcdn.com\/bphoto\/mQIyZfRhvWD5ZIDimVENqQ\/o.jpg","is_closed":false,"url":"https:\/\/www.yelp.com\/biz\/mangal-turkish-grill-sunnyvale?adjust_creative=wNVJ2NQ-VXEtJk4AjWcSCg&utm_campaign=yelp_api_v3&utm_medium=api_v3_business_search&utm_source=wNVJ2NQ-VXEtJk4AjWcSCg","review_count":518,"categories":[{"alias":"steak","title":"Steakhouses"},{"alias":"bbq","title":"Barbeque"},{"alias":"breakfast_brunch","title":"Breakfast & Brunch"}],"rating":4.7,"coordinates":{"latitude":37.401767,"longitude":-122.027477},"transactions":["delivery","pickup"],"location":{"address1":"502 Ross Dr","address2":null,"address3":"","city":"Sunnyvale","zip_code":"94089","country":"US","state":"CA","display_address":["502 Ross Dr","Sunnyvale, CA 94089"]},"phone":"+14087471888","display_phone":"(408) 747-1888","distance":3090.8165690634,"business_hours":[{"open":[{"is_overnight":false,"start":"1100","end":"1400","day":1},{"is_overnight":false,"start":"1700","end":"2200","day":1},{"is_overnight":false,"start":"1100","end":"1400","day":2},{"is_overnight":false,"start":"1700","end":"2200","day":2},{"is_overnight":false,"start":"1100","end":"1400","day":3},{"is_overnight":false,"start":"1700","end":"2200","day":3},{"is_overnight":false,"start":"1100","end":"1400","day":4},{"is_overnight":false,"start":"1700","end":"2200","day":4},{"is_overnight":false,"start":"0900","end":"1400","day":5},{"is_overnight":false,"start":"1700","end":"2200","day":5},{"is_overnight":false,"start":"0900","end":"1400","day":6},{"is_overnight":false,"start":"1700","end":"2200","day":6}],"hours_type":"REGULAR","is_open_now":false}],"attributes":{"business_temp_closed":null,"menu_url":"https:\/\/www.mangalsv.com\/menus-1","open24_hours":null,"waitlist_reservation":null},"price":"$$"}
{"id":"WZpCTPDFiXyVjkwYeIZfAQ","alias":"la-marea-of-the-sea-sunnyvale-2","name":"La Marea of the Sea","image_url":"https:\/\/s3-media2.fl.yelpcdn.com\/bphoto\/cMLL06RhCfw5OowcwhS3zQ\/o.jpg","is_closed":false,"url":"https:\/\/www.yelp.com\/biz\/la-marea-of-the-sea-sunnyvale-2?adjust_creative=wNVJ2NQ-VXEtJk4AjWcSCg&utm_campaign=yelp_api_v3&utm_medium=api_v3_business_search&utm_source=wNVJ2NQ-VXEtJk4AjWcSCg","review_count":50,"categories":[{"alias":"seafood","title":"Seafood"},{"alias":"foodstands","title":"Food Stands"}],"rating":4.7,"coordinates":{"latitude":37.378164,"longitude":-122.030741},"transactions":[],"location":{"address1":"121 W Evelyn Ave","address2":"","address3":"","city":"Sunnyvale","zip_code":"94086","country":"US","state":"CA","display_address":["121 W Evelyn Ave","Sunnyvale, CA 94086"]},"phone":"+18313313432","display_phone":"(831) 331-3432","distance":725.2361544447,"business_hours":[{"open":[{"is_overnight":false,"start":"0830","end":"1300","day":5}],"hours_type":"REGULAR","is_open_now":false}],"attributes":{"business_temp_closed":null,"menu_url":null,"open24_hours":null,"waitlist_reservation":null},"price":"$"}
{"id":"2kRKfCio8e77eRXuqeNG9w","alias":"chaat-bhavan-mountain-view-mountain-view-3","name":"Chaat Bhavan - Mountain View","image_url":"https:\/\/s3-media4.fl.yelpcdn.com\/bphoto\/pu6rK3o3d58BkwNRtZvY9A\/o.jpg","is_closed":false,"url":"https:\/\/www.yelp.com\/biz\/chaat-bhavan-mountain-view-mountain-view-3?adjust_creative=wNVJ2NQ-VXEtJk4AjWcSCg&utm_campaign=yelp_api_v3&utm_medium=api_v3_business_search&utm_source=wNVJ2NQ-VXEtJk4AjWcSCg","review_count":437,"categories":[{"alias":"indpak","title":"Indian"},{"alias":"vegetarian","title":"Vegetarian"},{"alias":"catering","title":"Caterers"}],"rating":4.7,"coordinates":{"latitude":37.3785010483,"longitude":-122.0710586699},"transactions":["delivery","pickup"],"location":{"address1":"165 E El Camino Real","address2":null,"address3":"","city":"Mountain View","zip_code":"94040","country":"US","state":"CA","display_address":["165 E El Camino Real","Mountain View, CA 94040"]},"phone":"+16509651111","display_phone":"(650) 965-1111","distance":4148.3687123009,"business_hours":[{"open":[{"is_overnight":false,"start":"1030","end":"2200","day":0},{"is_overnight":false,"start":"1030","end":"2200","day":1},{"is_overnight":false,"start":"1030","end":"2200","day":2},{"is_overnight":false,"start":"1030","end":"2200","day":3},{"is_overnight":false,"start":"1030","end":"2200","day":4},{"is_overnight":false,"start":"1030","end":"2200","day":5},{"is_overnight":false,"start":"1030","end":"2200","day":6}],"hours_type":"REGULAR","is_open_now":true}],"attributes":{"business_temp_closed":null,"menu_url":"https:\/\/www.chaatbhavan.com\/mountain-view\/","open24_hours":null,"waitlist_reservation":true},"price":"$$"}
{"id":"OEMISFM8YxrZgWAIX3W1Tg","alias":"california-momo-kitchen-sunnyvale","name":"California MoMo Kitchen","image_url":"https:\/\/s3-media2.fl.yelpcdn.com\/bphoto\/EYzwH75nYFBQCk8IcnxD3Q\/o.jpg","is_closed":false,"url":"https:\/\/www.yelp.com\/biz\/california-momo-kitchen-sunnyvale?adjust_creative=wNVJ2NQ-VXEtJk4AjWcSCg&utm_campaign=yelp_api_v3&utm_medium=api_v3_business_search&utm_source=wNVJ2NQ-VXEtJk4AjWcSCg","review_count":167,"categories":[{"alias":"himalayan","title":"Himalayan\/Nepalese"},{"alias":"halal","title":"Halal"},{"alias":"indpak","title":"Indian"}],"rating":4.7,"coordinates":{"latitude":37.389247,"longitude":-122.004175},"transactions":["delivery","pickup"],"location":{"address1":"913 E Duane Ave","address2":null,"address3":"","city":"Sunnyvale","zip_code":"94085","country":"US","state":"CA","display_address":["913 E Duane Ave","Sunnyvale, CA 94085"]},"phone":"+14087435857","display_phone":"(408) 743-5857","distance":2458.8308855714,"business_hours":[{"open":[{"is_overnight":false,"start":"1100","end":"2100","day":0},{"is_overnight":false,"start":"1100","end":"2100","day":1},{"is_overnight":false,"start":"1100","end":"2100","day":2},{"is_overnight":false,"start":"1100","end":"2100","day":3},{"is_overnight":false,"start":"1100","end":"2200","day":4},{"is_overnight":false,"start":"1130","end":"2200","day":5},{"is_overnight":false,"start":"1130","end":"2100","day":6}],"hours_type":"REGULAR","is_open_now":false}],"attributes":{"business_temp_closed":null,"menu_url":null,"open24_hours":null,"waitlist_reservation":null},"price":"$$"}
{"id":"Zb7217fH3pUn_Sf0OE1Ieg","alias":"giwa-santa-clara","name":"GIWA","image_url":"https:\/\/s3-media4.fl.yelpcdn.com\/bphoto\/SQvzp8NlZ6Jn_QL1fF5asw\/o.jpg","is_closed":false,"url":"https:\/\/www.yelp.com\/biz\/giwa-santa-clara?adjust_creative=wNVJ2NQ-VXEtJk4AjWcSCg&utm_campaign=yelp_api_v3&utm_medium=api_v3_business_search&utm_source=wNVJ2NQ-VXEtJk4AjWcSCg","review_count":101,"categories":[{"alias":"breakfast_brunch","title":"Breakfast & Brunch"},{"alias":"cafes","title":"Cafes"},{"alias":"tradamerican","title":"American"}],"rating":4.7,"coordinates":{"latitude":37.351409,"longitude":-122.000025},"transactions":[],"location":{"address1":"1494 Halford Ave","address2":null,"address3":null,"city":"Santa Clara","zip_code":"95051","country":"US","state":"CA","display_address":["1494 Halford Ave","Santa Clara, CA 95051"]},"phone":"+16692797922","display_phone":"(669) 279-7922","distance":3303.3456128303,"business_hours":[{"open":[{"is_overnight":false,"start":"0800","end":"1600","day":0},{"is_overnight":false,"start":"0800","end":"1600","day":1},{"is_overnight":false,"start":"0800","end":"1600","day":2},{"is_overnight":false,"start":"0800","end":"1600","day":3},{"is_overnight":false,"start":"0800","end":"1600","day":4},{"is_overnight":false,"start":"0800","end":"1600","day":5},{"is_overnight":false,"start":"0800","end":"1600","day":6}],"hours_type":"REGULAR","is_open_now":false}],"attributes":{"business_temp_closed":null,"menu_url":null,"open24_hours":null,"waitlist_reservation":true},"price":null}
{"id":"-Z-aO9gwyPEtgarO_iXraw","alias":"el-califas-tacos-sunnyvale","name":"El Califas Tacos","image_url":"https:\/\/s3-media2.fl.yelpcdn.com\/bphoto\/_5e1eWamZLborz_--4jK1g\/o.jpg","is_closed":false,"url":"https:\/\/www.yelp.com\/biz\/el-califas-tacos-sunnyvale?adjust_creative=wNVJ2NQ-VXEtJk4AjWcSCg&utm_campaign=yelp_api_v3&utm_medium=api_v3_business_search&utm_source=wNVJ2NQ-VXEtJk4AjWcSCg","review_count":246,"categories":[{"alias":"foodtrucks","title":"Food Trucks"},{"alias":"tacos","title":"Tacos"}],"rating":4.7,"coordinates":{"latitude":37.389521,"longitude":-122.030975},"transactions":["delivery","pickup"],"location":{"address1":"499 N Mathilda Ave","address2":"","address3":null,"city":"Sunnyvale","zip_code":"94085","country":"US","state":"CA","display_address":["499 N Mathilda Ave","Sunnyvale, CA 94085"]},"phone":"+14088327559","display_phone":"(408) 832-7559","distance":1822.9343601455,"business_hours":[{"open":[{"is_overnight":false,"start":"1000","end":"1800","day":0},{"is_overnight":false,"start":"1000","end":"1800","day":1},{"is_overnight":false,"start":"1000","end":"1800","day":2},{"is_overnight":false,"start":"1000","end":"1800","day":3},{"is_overnight":false,"start":"1000","end":"1800","day":4},{"is_overnight":false,"start":"1000","end":"1400","day":5}],"hours_type":"REGULAR","is_open_now":false}],"attributes":{"business_temp_closed":null,"menu_url":"https:\/\/elcalifastacos.com\/menu","open24_hours":null,"waitlist_reservation":null},"price":"$"}
{"id":"uX9SQdryr4VR5lBln8SngA","alias":"el-califas-tacos-mountain-view-2","name":"El Califas Tacos","image_url":"https:\/\/s3-media2.fl.yelpcdn.com\/bphoto\/OpLsWGxh-a2YtDbNsIZSGw\/o.jpg","is_closed":false,"url":"https:\/\/www.yelp.com\/biz\/el-califas-tacos-mountain-view-2?adjust_creative=wNVJ2NQ-VXEtJk4AjWcSCg&utm_campaign=yelp_api_v3&utm_medium=api_v3_business_search&utm_source=wNVJ2NQ-VXEtJk4AjWcSCg","review_count":64,"categories":[{"alias":"tacos","title":"Tacos"},{"alias":"foodtrucks","title":"Food Trucks"}],"rating":4.7,"coordinates":{"latitude":37.3999406687,"longitude":-122.0730551},"transactions":["delivery","pickup"],"location":{"address1":"495 Moffett Blvd","address2":null,"address3":null,"city":"Mountain View","zip_code":"94043","country":"US","state":"CA","display_address":["495 Moffett Blvd","Mountain View, CA 94043"]},"phone":"+19257198562","display_phone":"(925) 719-8562","distance":5174.4923247695,"business_hours":[{"open":[{"is_overnight":false,"start":"1000","end":"1800","day":0},{"is_overnight":false,"start":"1000","end":"1800","day":1},{"is_overnight":false,"start":"1000","end":"1800","day":2},{"is_overnight":false,"start":"1000","end":"1800","day":3},{"is_overnight":false,"start":"1000","end":"1800","day":4}],"hours_type":"REGULAR","is_open_now":false}],"attributes":{"business_temp_closed":null,"menu_url":"https:\/\/elcalifastacos.com\/menu","open24_hours":null,"waitlist_reservation":null},"price":null}
{"id":"RHO60RvK_EQVyj6ADCjzbg","alias":"las-minas-guatemalan-cuisine-sunnyvale-2","name":"Las Minas Guatemalan Cuisine","image_url":"https:\/\/s3-media1.fl.yelpcdn.com\/bphoto\/HfUNBjyKBL-ic4zS1zuykw\/o.jpg","is_closed":false,"url":"https:\/\/www.yelp.com\/biz\/las-minas-guatemalan-cuisine-sunnyvale-2?adjust_creative=wNVJ2NQ-VXEtJk4AjWcSCg&utm_campaign=yelp_api_v3&utm_medium=api_v3_business_search&utm_source=wNVJ2NQ-VXEtJk4AjWcSCg","review_count":7,"categories":[{"alias":"foodtrucks","title":"Food Trucks"},{"alias":"latin","title":"Latin American"}],"rating":4.7,"coordinates":{"latitude":37.375079,"longitude":-122.058357},"transactions":[],"location":{"address1":"1255 W El Camino Real","address2":"","address3":null,"city":"Sunnyvale","zip_code":"94087","country":"US","state":"CA","display_address":["1255 W El Camino Real","Sunnyvale, CA 94087"]},"phone":"+14084807505","display_phone":"(408) 480-7505","distance":2997.8723755464,"business_hours":[{"open":[{"is_overnight":false,"start":"1100","end":"2200","day":0},{"is_overnight":false,"start":"1100","end":"2200","day":1},{"is_overnight":false,"start":"1100","end":"2200","day":2},{"is_overnight":false,"start":"1100","end":"2200","day":3},{"is_overnight":false,"start":"0900","end":"2330","day":4},{"is_overnight":false,"start":"0900","end":"2330","day":5}],"hours_type":"REGULAR","is_open_now":true}],"attributes":{"business_temp_closed":null,"menu_url":"https:\/\/www.lasminasguatemalancuisine.com\/menu","open24_hours":null,"waitlist_reservation":null},"price":null}
{"id":"k5zXdbb0K33ZnagIrRWXRg","alias":"dosas-n-more-sunnyvale-2","name":"Dosas 'N' More","image_url":"https:\/\/s3-media1.fl.yelpcdn.com\/bphoto\/fpnef0LCEg6lNiOzrIimkA\/o.jpg","is_closed":false,"url":"https:\/\/www.yelp.com\/biz\/dosas-n-more-sunnyvale-2?adjust_creative=wNVJ2NQ-VXEtJk4AjWcSCg&utm_campaign=yelp_api_v3&utm_medium=api_v3_business_search&utm_source=wNVJ2NQ-VXEtJk4AjWcSCg","review_count":10,"categories":[{"alias":"foodtrucks","title":"Food Trucks"},{"alias":"indpak","title":"Indian"},{"alias":"creperies","title":"Creperies"}],"rating":4.7,"coordinates":{"latitude":37.37522,"longitude":-122.05832},"transactions":[],"location":{"address1":"1255 W El Camino Real","address2":null,"address3":"","city":"Sunnyvale","zip_code":"94087","country":"US","state":"CA","display_address":["1255 W El Camino Real","Sunnyvale, CA 94087"]},"phone":"+14086502091","display_phone":"(408) 650-2091","distance":2995.4386243146,"business_hours":[{"open":[{"is_overnight":false,"start":"1800","end":"2130","day":3},{"is_overnight":false,"start":"1800","end":"2130","day":4},{"is_overnight":false,"start":"1200","end":"2130","day":5},{"is_overnight":false,"start":"1200","end":"2130","day":6}],"hours_type":"REGULAR","is_open_now":false}],"attributes":{"business_temp_closed":1756710000,"menu_url":null,"open24_hours":null,"waitlist_reservation":null},"price":null}
{"id":"76136Yv4JOgcns3dFdodHw","alias":"mikiya-wagyu-shabu-house-santa-clara-3","name":"Mikiya Wagyu Shabu House","image_url":"https:\/\/s3-media3.fl.yelpcdn.com\/bphoto\/HBoHH2vFVkZPnXRfZK-2FQ\/o.jpg","is_closed":false,"url":"https:\/\/www.yelp.com\/biz\/mikiya-wagyu-shabu-house-santa-clara-3?adjust_creative=wNVJ2NQ-VXEtJk4AjWcSCg&utm_campaign=yelp_api_v3&utm_medium=api_v3_business_search&utm_source=wNVJ2NQ-VXEtJk4AjWcSCg","review_count":1849,"categories":[{"alias":"hotpot","title":"Hot Pot"},{"alias":"japanese","title":"Japanese"},{"alias":"asianfusion","title":"Asian Fusion"}],"rating":4.7,"coordinates":{"latitude":37.337486,"longitude":-121.995091},"transactions":["restaurant_reservation"],"location":{"address1":"3590 Homestead Rd","address2":null,"address3":"","city":"Santa Clara","zip_code":"95051","country":"US","state":"CA","display_address":["3590 Homestead Rd","Santa Clara, CA 95051"]},"phone":"+14086896244","display_phone":"(408) 689-6244","distance":4816.3522540303,"business_hours":[{"open":[{"is_overnight":false,"start":"1130","end":"2200","day":0},{"is_overnight":false,"start":"1130","end":"2200","day":1},{"is_overnight":false,"start":"1130","end":"2200","day":2},{"is_overnight":false,"start":"1130","end":"2200","day":3},{"is_overnight":false,"start":"1130","end":"2300","day":4},{"is_overnight":false,"start":"1130","end":"2300","day":5},{"is_overnight":false,"start":"1130","end":"2200","day":6}],"hours_type":"REGULAR","is_open_now":true}],"attributes":{"business_temp_closed":null,"menu_url":"https:\/\/mikiyashabu.com\/menu\/","open24_hours":null,"waitlist_reservation":true},"price":"$$$$"}
{"id":"mOBQWxvTigoZeH1hM7AULA","alias":"eggmania-sunnyvale-3","name":"Eggmania","image_url":"https:\/\/s3-media1.fl.yelpcdn.com\/bphoto\/flIyyiFRLFdfriqFiBM8fA\/o.jpg","is_closed":false,"url":"https:\/\/www.yelp.com\/biz\/eggmania-sunnyvale-3?adjust_creative=wNVJ2NQ-VXEtJk4AjWcSCg&utm_campaign=yelp_api_v3&utm_medium=api_v3_business_search&utm_source=wNVJ2NQ-VXEtJk4AjWcSCg","review_count":88,"categories":[{"alias":"foodtrucks","title":"Food Trucks"},{"alias":"foodstands","title":"Food Stands"}],"rating":4.7,"coordinates":{"latitude":37.3518249599,"longitude":-122.0107401},"transactions":["delivery","pickup"],"location":{"address1":"962 E El Camino Real","address2":null,"address3":null,"city":"Sunnyvale","zip_code":"94087","country":"US","state":"CA","display_address":["962 E El Camino Real","Sunnyvale, CA 94087"]},"phone":"+16693176979","display_phone":"(669) 317-6979","distance":2744.3422988783,"business_hours":[{"open":[{"is_overnight":false,"start":"1200","end":"2200","day":1},{"is_overnight":false,"start":"1200","end":"2200","day":2},{"is_overnight":false,"start":"1200","end":"2200","day":3},{"is_overnight":false,"start":"1200","end":"2230","day":4},{"is_overnight":false,"start":"1200","end":"2230","day":5},{"is_overnight":false,"start":"1200","end":"2200","day":6}],"hours_type":"REGULAR","is_open_now":false}],"attributes":{"business_temp_closed":null,"menu_url":"https:\/\/www.eggmania.com\/menu\/","open24_hours":null,"waitlist_reservation":null},"price":"$$"}
{"id":"Kj5cgIzbCWlG1LgHIeXY7w","alias":"sizzling-pot-house-santa-clara","name":"Sizzling Pot House","image_url":"https:\/\/s3-media3.fl.yelpcdn.com\/bphoto\/LmdTIYpwbUBBvkTliyXD4Q\/o.jpg","is_closed":false,"url":"https:\/\/www.yelp.com\/biz\/sizzling-pot-house-santa-clara?adjust_creative=wNVJ2NQ-VXEtJk4AjWcSCg&utm_campaign=yelp_api_v3&utm_medium=api_v3_business_search&utm_source=wNVJ2NQ-VXEtJk4AjWcSCg","review_count":63,"categories":[{"alias":"chinese","title":"Chinese"}],"rating":4.7,"coordinates":{"latitude":37.3528241997,"longitude":-121.9760469446},"transactions":["delivery","pickup"],"location":{"address1":"2725 El Camino Real","address2":"Ste 101","address3":"","city":"Santa Clara","zip_code":"95051","country":"US","state":"CA","display_address":["2725 El Camino Real","Ste 101","Santa Clara, CA 95051"]},"phone":"+14086030498","display_phone":"(408) 603-0498","distance":4881.9168641282,"business_hours":[{"open":[{"is_overnight":false,"start":"1100","end":"1430","day":0},{"is_overnight":false,"start":"1630","end":"2030","day":0},{"is_overnight":false,"start":"1100","end":"1430","day":1},{"is_overnight":false,"start":"1630","end":"2030","day":1},{"is_overnight":false,"start":"1100","end":"1430","day":2},{"is_overnight":false,"start":"1630","end":"2030","day":2},{"is_overnight":false,"start":"1100","end":"1430","day":3},{"is_overnight":false,"start":"1630","end":"2030","day":3},{"is_overnight":false,"start":"1100","end":"1500","day":4},{"is_overnight":false,"start":"1700","end":"2100","day":4},{"is_overnight":false,"start":"1100","end":"1500","day":5},{"is_overnight":false,"start":"1700","end":"2100","day":5},{"is_overnight":false,"start":"1100","end":"1500","day":6},{"is_overnight":false,"start":"1700","end":"2100","day":6}],"hours_type":"REGULAR","is_open_now":false}],"attributes":{"business_temp_closed":null,"menu_url":null,"open24_hours":null,"waitlist_reservation":null},"price":null}
{"id":"DtztT6Lus4lpq_ucBupM3g","alias":"valley-goat-sunnyvale-2","name":"Valley Goat","image_url":"https:\/\/s3-media1.fl.yelpcdn.com\/bphoto\/Ia7rp2uE5w47AILoepxnlw\/o.jpg","is_closed":false,"url":"https:\/\/www.yelp.com\/biz\/valley-goat-sunnyvale-2?adjust_creative=wNVJ2NQ-VXEtJk4AjWcSCg&utm_campaign=yelp_api_v3&utm_medium=api_v3_business_search&utm_source=wNVJ2NQ-VXEtJk4AjWcSCg","review_count":67,"categories":[{"alias":"newamerican","title":"New American"},{"alias":"tapasmallplates","title":"Tapas\/Small Plates"},{"alias":"cocktailbars","title":"Cocktail Bars"}],"rating":4.7,"coordinates":{"latitude":37.4043878884,"longitude":-122.0247026265},"transactions":[],"location":{"address1":"1100 N Mathilda Ave","address2":null,"address3":null,"city":"Sunnyvale","zip_code":"94089","country":"US","state":"CA","display_address":["1100 N Mathilda Ave","Sunnyvale, CA 94089"]},"phone":"+14089009470","display_phone":"(408) 900-9470","distance":3382.844903017,"business_hours":[{"open":[{"is_overnight":false,"start":"1100","end":"2200","day":0},{"is_overnight":false,"start":"1100","end":"2200","day":1},{"is_overnight":false,"start":"1100","end":"2200","day":2},{"is_overnight":false,"start":"1100","end":"2200","day":3},{"is_overnight":false,"start":"1100","end":"2200","day":4},{"is_overnight":false,"start":"1100","end":"2200","day":5},{"is_overnight":false,"start":"1100","end":"2200","day":6}],"hours_type":"REGULAR","is_open_now":true}],"attributes":{"business_temp_closed":null,"menu_url":"https:\/\/www.valleygoatsv.com\/menu","open24_hours":null,"waitlist_reservation":null},"price":null}
{"id":"hHbTtdglkuRAUD4S_4FNDA","alias":"oh-baby-sushi-sunnyvale","name":"Oh Baby Sushi","image_url":"https:\/\/s3-media3.fl.yelpcdn.com\/bphoto\/rQY-I-RE47FGFfei-SxhwA\/o.jpg","is_closed":false,"url":"https:\/\/www.yelp.com\/biz\/oh-baby-sushi-sunnyvale?adjust_creative=wNVJ2NQ-VXEtJk4AjWcSCg&utm_campaign=yelp_api_v3&utm_medium=api_v3_business_search&utm_source=wNVJ2NQ-VXEtJk4AjWcSCg","review_count":136,"categories":[{"alias":"vegetarian","title":"Vegetarian"},{"alias":"sushi","title":"Sushi Bars"}],"rating":4.7,"coordinates":{"latitude":37.407442,"longitude":-122.01078},"transactions":[],"location":{"address1":"1200 Crossman Ave","address2":null,"address3":"","city":"Sunnyvale","zip_code":"94089","country":"US","state":"CA","display_address":["1200 Crossman Ave","Sunnyvale, CA 94089"]},"phone":"+14086852128","display_phone":"(408) 685-2128","distance":3914.5265251893,"business_hours":[{"open":[{"is_overnight":false,"start":"1630","end":"2000","day":1},{"is_overnight":false,"start":"1630","end":"2000","day":2},{"is_overnight":false,"start":"1630","end":"2000","day":3},{"is_overnight":false,"start":"1630","end":"2030","day":4},{"is_overnight":false,"start":"1130","end":"1330","day":5},{"is_overnight":false,"start":"1630","end":"2030","day":5},{"is_overnight":false,"start":"1130","end":"1330","day":6},{"is_overnight":false,"start":"1630","end":"2000","day":6}],"hours_type":"REGULAR","is_open_now":false}],"attributes":{"business_temp_closed":null,"menu_url":null,"open24_hours":null,"waitlist_reservation":null},"price":null}
{"id":"_IJgHfasfqXPIhuv6ckubw","alias":"quiroga-taqueria-sunnyvale-5","name":"Quiroga Taqueria","image_url":"https:\/\/s3-media1.fl.yelpcdn.com\/bphoto\/ob9TYfzaRLkdUbBSrW_Wew\/o.jpg","is_closed":false,"url":"https:\/\/www.yelp.com\/biz\/quiroga-taqueria-sunnyvale-5?adjust_creative=wNVJ2NQ-VXEtJk4AjWcSCg&utm_campaign=yelp_api_v3&utm_medium=api_v3_business_search&utm_source=wNVJ2NQ-VXEtJk4AjWcSCg","review_count":74,"categories":[{"alias":"mexican","title":"Mexican"},{"alias":"foodtrucks","title":"Food Trucks"}],"rating":4.6,"coordinates":{"latitude":37.3801141864,"longitude":-121.9964766875},"transactions":["delivery"],"location":{"address1":"295 Lawrence Expy","address2":"","address3":null,"city":"Sunnyvale","zip_code":"94085","country":"US","state":"CA","display_address":["295 Lawrence Expy","Sunnyvale, CA 94085"]},"phone":"+18312455897","display_phone":"(831) 245-5897","distance":2565.4166083825,"business_hours":[{"open":[{"is_overnight":false,"start":"0830","end":"1500","day":0},{"is_overnight":false,"start":"0830","end":"1500","day":1},{"is_overnight":false,"start":"0830","end":"1500","day":2},{"is_overnight":false,"start":"0830","end":"1500","day":3},{"is_overnight":false,"start":"0830","end":"1500","day":4},{"is_overnight":false,"start":"0830","end":"1400","day":5}],"hours_type":"REGULAR","is_open_now":false}],"attributes":{"business_temp_closed":null,"menu_url":null,"open24_hours":null,"waitlist_reservation":null},"price":"$"}
{"id":"yitZZOCfhHCqSrNMB5iiUQ","alias":"margaritas-taqueria-sunnyvale-2","name":"Margaritas Taqueria","image_url":"https:\/\/s3-media1.fl.yelpcdn.com\/bphoto\/rqmlQENhq2ZrzZWcnwn3RQ\/o.jpg","is_closed":false,"url":"https:\/\/www.yelp.com\/biz\/margaritas-taqueria-sunnyvale-2?adjust_creative=wNVJ2NQ-VXEtJk4AjWcSCg&utm_campaign=yelp_api_v3&utm_medium=api_v3_business_search&utm_source=wNVJ2NQ-VXEtJk4AjWcSCg","review_count":369,"categories":[{"alias":"foodtrucks","title":"Food Trucks"},{"alias":"mexican","title":"Mexican"}],"rating":4.6,"coordinates":{"latitude":37.3381746035,"longitude":-121.9970485624},"transactions":["delivery","pickup"],"location":{"address1":"1175 E Homestead","address2":null,"address3":"","city":"Sunnyvale","zip_code":"94087","country":"US","state":"CA","display_address":["1175 E Homestead","Sunnyvale, CA 94087"]},"phone":"+16509433873","display_phone":"(650) 943-3873","distance":4659.2572688605,"business_hours":[{"open":[{"is_overnight":false,"start":"0930","end":"2000","day":0},{"is_overnight":false,"start":"0930","end":"2000","day":1},{"is_overnight":false,"start":"0930","end":"2000","day":2},{"is_overnight":false,"start":"0930","end":"2000","day":3},{"is_overnight":false,"start":"0930","end":"1730","day":4},{"is_overnight":false,"start":"0930","end":"1800","day":5},{"is_overnight":false,"start":"0930","end":"1800","day":6}],"hours_type":"REGULAR","is_open_now":false}],"attributes":{"business_temp_closed":null,"menu_url":"https:\/\/margaritastaqueriaca.com\/services\/","open24_hours":null,"waitlist_reservation":null},"price":"$$"}
{"id":"2-Z7h0DsHlUw-h6zwXeXxw","alias":"house-of-tiffins-sunnyvale","name":"House of Tiffins","image_url":"https:\/\/s3-media1.fl.yelpcdn.com\/bphoto\/k9y0PWjwxyJPYFzgO9UWUA\/o.jpg","is_closed":false,"url":"https:\/\/www.yelp.com\/biz\/house-of-tiffins-sunnyvale?adjust_creative=wNVJ2NQ-VXEtJk4AjWcSCg&utm_campaign=yelp_api_v3&utm_medium=api_v3_business_search&utm_source=wNVJ2NQ-VXEtJk4AjWcSCg","review_count":35,"categories":[{"alias":"foodtrucks","title":"Food Trucks"},{"alias":"indpak","title":"Indian"}],"rating":4.6,"coordinates":{"latitude":37.3752366285,"longitude":-122.0583109169},"transactions":[],"location":{"address1":"1255 W El Camino Real","address2":"","address3":null,"city":"Sunnyvale","zip_code":"94087","country":"US","state":"CA","display_address":["1255 W El Camino Real","Sunnyvale, CA 94087"]},"phone":"+14085901888","display_phone":"(408) 590-1888","distance":2994.5764856661,"business_hours":[{"open":[{"is_overnight":false,"start":"1600","end":"2100","day":4},{"is_overnight":false,"start":"1600","end":"2100","day":5},{"is_overnight":false,"start":"1600","end":"2100","day":6}],"hours_type":"REGULAR","is_open_now":false}],"attributes":{"business_temp_closed":null,"menu_url":"https:\/\/www.hottiffins.com\/menu","open24_hours":null,"waitlist_reservation":null},"price":null}
{"id":"UVMRiVsf_PmRHwzmI6Ln3A","alias":"hironori-craft-ramen-cupertino","name":"HiroNori Craft Ramen","image_url":"https:\/\/s3-media2.fl.yelpcdn.com\/bphoto\/t7lIMdHr47VXK4bEX_PrKw\/o.jpg","is_closed":false,"url":"https:\/\/www.yelp.com\/biz\/hironori-craft-ramen-cupertino?adjust_creative=wNVJ2NQ-VXEtJk4AjWcSCg&utm_campaign=yelp_api_v3&utm_medium=api_v3_business_search&utm_source=wNVJ2NQ-VXEtJk4AjWcSCg","review_count":1249,"categories":[{"alias":"ramen","title":"Ramen"},{"alias":"noodles","title":"Noodles"}],"rating":4.6,"coordinates":{"latitude":37.33544,"longitude":-122.01444},"transactions":["delivery"],"location":{"address1":"10815 N Wolfe Rd","address2":"Unit 104","address3":"","city":"Cupertino","zip_code":"95014","country":"US","state":"CA","display_address":["10815 N Wolfe Rd","Unit 104","Cupertino, CA 95014"]},"phone":"+14089823820","display_phone":"(408) 982-3820","distance":4364.4207532704,"business_hours":[{"open":[{"is_overnight":false,"start":"1100","end":"2100","day":0},{"is_overnight":false,"start":"1100","end":"2100","day":1},{"is_overnight":false,"start":"1100","end":"2100","day":2},{"is_overnight":false,"start":"1100","end":"2100","day":3},{"is_overnight":false,"start":"1100","end":"2200","day":4},{"is_overnight":false,"start":"1100","end":"2200","day":5},{"is_overnight":false,"start":"1100","end":"2200","day":6}],"hours_type":"REGULAR","is_open_now":false}],"attributes":{"business_temp_closed":null,"menu_url":"https:\/\/hironori.com\/menu","open24_hours":null,"waitlist_reservation":true},"price":"$$"}
{"id":"PVMuwUL0xYqukfUpXdcBcQ","alias":"pav-bhaji-and-more-sunnyvale-3","name":"Pav Bhaji and More","image_url":"https:\/\/s3-media3.fl.yelpcdn.com\/bphoto\/mkFO5y0YfEM4f7IRsKLVjw\/o.jpg","is_closed":false,"url":"https:\/\/www.yelp.com\/biz\/pav-bhaji-and-more-sunnyvale-3?adjust_creative=wNVJ2NQ-VXEtJk4AjWcSCg&utm_campaign=yelp_api_v3&utm_medium=api_v3_business_search&utm_source=wNVJ2NQ-VXEtJk4AjWcSCg","review_count":197,"categories":[{"alias":"indpak","title":"Indian"},{"alias":"foodtrucks","title":"Food Trucks"}],"rating":4.6,"coordinates":{"latitude":37.3705422289,"longitude":-122.0568944059},"transactions":["delivery","pickup"],"location":{"address1":"750 S Bernardo Ave","address2":null,"address3":null,"city":"Sunnyvale","zip_code":"94087","country":"US","state":"CA","display_address":["750 S Bernardo Ave","Sunnyvale, CA 94087"]},"phone":"+14086052994","display_phone":"(408) 605-2994","distance":2891.331500961,"business_hours":[{"open":[{"is_overnight":false,"start":"1200","end":"2100","day":0},{"is_overnight":false,"start":"1200","end":"2100","day":1},{"is_overnight":false,"start":"1200","end":"2100","day":2},{"is_overnight":false,"start":"1200","end":"2100","day":3},{"is_overnight":false,"start":"1200","end":"2100","day":4},{"is_overnight":false,"start":"1200","end":"2100","day":5},{"is_overnight":false,"start":"1200","end":"2100","day":6}],"hours_type":"REGULAR","is_open_now":false}],"attributes":{"business_temp_closed":null,"menu_url":null,"open24_hours":null,"waitlist_reservation":null},"price":"$$"}
{"id":"COnwejdkHeQS1ThK0VSfHg","alias":"la-picosita-azteca-sunnyvale","name":"La Picosita Azteca","image_url":"https:\/\/s3-media4.fl.yelpcdn.com\/bphoto\/nbFb9ke5WLePfMQpk4q1YQ\/o.jpg","is_closed":false,"url":"https:\/\/www.yelp.com\/biz\/la-picosita-azteca-sunnyvale?adjust_creative=wNVJ2NQ-VXEtJk4AjWcSCg&utm_campaign=yelp_api_v3&utm_medium=api_v3_business_search&utm_source=wNVJ2NQ-VXEtJk4AjWcSCg","review_count":15,"categories":[{"alias":"foodtrucks","title":"Food Trucks"},{"alias":"mexican","title":"Mexican"}],"rating":4.6,"coordinates":{"latitude":37.387662,"longitude":-122.023562},"transactions":[],"location":{"address1":"259 E Maude Ave","address2":"","address3":"","city":"Sunnyvale","zip_code":"94085","country":"US","state":"CA","display_address":["259 E Maude Ave","Sunnyvale, CA 94085"]},"phone":"+14083175241","display_phone":"(408) 317-5241","distance":1525.0098068784,"business_hours":[{"open":[{"is_overnight":false,"start":"1100","end":"2100","day":0},{"is_overnight":false,"start":"1100","end":"2100","day":1},{"is_overnight":false,"start":"1100","end":"2100","day":2},{"is_overnight":false,"start":"1100","end":"2100","day":3},{"is_overnight":false,"start":"1100","end":"2100","day":4},{"is_overnight":false,"start":"1100","end":"2100","day":5}],"hours_type":"REGULAR","is_open_now":false}],"attributes":{"business_temp_closed":null,"menu_url":null,"open24_hours":null,"waitlist_reservation":null},"price":"$"}
{"id":"8SNGFcMWZkvS4GWDUL8w1Q","alias":"noon-o-kabob-san-jose-4","name":"Noon O Kabob","image_url":"https:\/\/s3-media1.fl.yelpcdn.com\/bphoto\/zzwOUBKRqT35-fl5yYZK-g\/o.jpg","is_closed":false,"url":"https:\/\/www.yelp.com\/biz\/noon-o-kabob-san-jose-4?adjust_creative=wNVJ2NQ-VXEtJk4AjWcSCg&utm_campaign=yelp_api_v3&utm_medium=api_v3_business_search&utm_source=wNVJ2NQ-VXEtJk4AjWcSCg","review_count":40,"categories":[{"alias":"foodtrucks","title":"Food Trucks"},{"alias":"kebab","title":"Kebab"},{"alias":"persian","title":"Persian\/Iranian"}],"rating":4.6,"coordinates":{"latitude":37.3940232,"longitude":-122.0288052},"transactions":[],"location":{"address1":null,"address2":null,"address3":null,"city":"San Jose","zip_code":"95101","country":"US","state":"CA","display_address":["San Jose, CA 95101"]},"phone":"+14083346777","display_phone":"(408) 334-6777","distance":2263.0816135098,"business_hours":[{"open":[{"is_overnight":false,"start":"1130","end":"1330","day":0},{"is_overnight":false,"start":"1130","end":"1330","day":1},{"is_overnight":false,"start":"1130","end":"1330","day":2},{"is_overnight":false,"start":"1130","end":"1330","day":3},{"is_overnight":false,"start":"1130","end":"1330","day":4},{"is_overnight":false,"start":"1130","end":"1330","day":5}],"hours_type":"REGULAR","is_open_now":false}],"attributes":{"business_temp_closed":null,"menu_url":"https:\/\/www.thenoonokabobtruck.com\/menu\/","open24_hours":null,"waitlist_reservation":null},"price":"$$"}
{"id":"TQq7drocA9jhMyiZACoX2A","alias":"ulavacharu-sweets-and-snacks-sunnyvale-2","name":"UlavacharU Sweets & Snacks","image_url":"https:\/\/s3-media3.fl.yelpcdn.com\/bphoto\/TxFJbWmXsIVBwhtTlU2auw\/o.jpg","is_closed":false,"url":"https:\/\/www.yelp.com\/biz\/ulavacharu-sweets-and-snacks-sunnyvale-2?adjust_creative=wNVJ2NQ-VXEtJk4AjWcSCg&utm_campaign=yelp_api_v3&utm_medium=api_v3_business_search&utm_source=wNVJ2NQ-VXEtJk4AjWcSCg","review_count":20,"categories":[{"alias":"indpak","title":"Indian"},{"alias":"desserts","title":"Desserts"},{"alias":"sandwiches","title":"Sandwiches"}],"rating":4.6,"coordinates":{"latitude":37.365689,"longitude":-122.028769},"transactions":["delivery","pickup"],"location":{"address1":"151 E El Camino Real","address2":null,"address3":"","city":"Sunnyvale","zip_code":"94087","country":"US","state":"CA","display_address":["151 E El Camino Real","Sunnyvale, CA 94087"]},"phone":"+14088884469","display_phone":"(408) 888-4469","distance":997.1538413737,"business_hours":[{"open":[{"is_overnight":false,"start":"1130","end":"2030","day":0},{"is_overnight":false,"start":"1130","end":"2030","day":1},{"is_overnight":false,"start":"1130","end":"2030","day":2},{"is_overnight":false,"start":"1130","end":"2030","day":3},{"is_overnight":false,"start":"1130","end":"2030","day":4},{"is_overnight":false,"start":"1130","end":"2030","day":5},{"is_overnight":false,"start":"1130","end":"2030","day":6}],"hours_type":"REGULAR","is_open_now":false}],"attributes":{"business_temp_closed":null,"menu_url":"https:\/\/ulavacharusweets.com\/menu","open24_hours":null,"waitlist_reservation":null},"price":null}
{"id":"4uW86PEcg7LCsd3td1oCLQ","alias":"happy-flower-eatery-and-boba-sunnyvale","name":"Happy Flower Eatery & Boba","image_url":"https:\/\/s3-media3.fl.yelpcdn.com\/bphoto\/l7ihEi41VCbgkfcnJ4vBag\/o.jpg","is_closed":false,"url":"https:\/\/www.yelp.com\/biz\/happy-flower-eatery-and-boba-sunnyvale?adjust_creative=wNVJ2NQ-VXEtJk4AjWcSCg&utm_campaign=yelp_api_v3&utm_medium=api_v3_business_search&utm_source=wNVJ2NQ-VXEtJk4AjWcSCg","review_count":169,"categories":[{"alias":"vietnamese","title":"Vietnamese"},{"alias":"vegan","title":"Vegan"},{"alias":"vegetarian","title":"Vegetarian"}],"rating":4.6,"coordinates":{"latitude":37.40654,"longitude":-121.9977},"transactions":["delivery","pickup"],"location":{"address1":"1274 Persian Dr","address2":null,"address3":"","city":"Sunnyvale","zip_code":"94089","country":"US","state":"CA","display_address":["1274 Persian Dr","Sunnyvale, CA 94089"]},"phone":"+14086578288","display_phone":"(408) 657-8288","distance":4328.6254846249,"business_hours":[{"open":[{"is_overnight":false,"start":"1100","end":"1400","day":0},{"is_overnight":false,"start":"1700","end":"2100","day":0},{"is_overnight":false,"start":"1100","end":"1400","day":2},{"is_overnight":false,"start":"1700","end":"2100","day":2},{"is_overnight":false,"start":"1100","end":"1400","day":3},{"is_overnight":false,"start":"1700","end":"2100","day":3},{"is_overnight":false,"start":"1100","end":"1400","day":4},{"is_overnight":false,"start":"1700","end":"2100","day":4},{"is_overnight":false,"start":"1100","end":"2100","day":5},{"is_overnight":false,"start":"1100","end":"2100","day":6}],"hours_type":"REGULAR","is_open_now":false}],"attributes":{"business_temp_closed":null,"menu_url":null,"open24_hours":null,"waitlist_reservation":null},"price":"$$"}
{"id":"JqQfknjrTEHshSzIuf4Mqw","alias":"desi-pizza-house-mountain-view","name":"Desi Pizza House","image_url":"https:\/\/s3-media1.fl.yelpcdn.com\/bphoto\/Ph7isSemeVEnZyMn1R0URg\/o.jpg","is_closed":false,"url":"https:\/\/www.yelp.com\/biz\/desi-pizza-house-mountain-view?adjust_creative=wNVJ2NQ-VXEtJk4AjWcSCg&utm_campaign=yelp_api_v3&utm_medium=api_v3_business_search&utm_source=wNVJ2NQ-VXEtJk4AjWcSCg","review_count":105,"categories":[{"alias":"pizza","title":"Pizza"},{"alias":"indpak","title":"Indian"}],"rating":4.6,"coordinates":{"latitude":37.3980808415,"longitude":-122.0751793433},"transactions":["delivery","pickup"],"location":{"address1":"327 Moffett Blvd","address2":null,"address3":"","city":"Mountain View","zip_code":"94043","country":"US","state":"CA","display_address":["327 Moffett Blvd","Mountain View, CA 94043"]},"phone":"+16509613301","display_phone":"(650) 961-3301","distance":5222.1450972062,"business_hours":[{"open":[{"is_overnight":false,"start":"1000","end":"2200","day":0},{"is_overnight":true,"start":"1000","end":"0100","day":1},{"is_overnight":true,"start":"1000","end":"0100","day":2},{"is_overnight":true,"start":"1000","end":"0100","day":3},{"is_overnight":true,"start":"1000","end":"0230","day":4},{"is_overnight":true,"start":"1000","end":"0230","day":5},{"is_overnight":true,"start":"1000","end":"0100","day":6}],"hours_type":"REGULAR","is_open_now":true}],"attributes":{"business_temp_closed":null,"menu_url":"https:\/\/www.desipizzahouse.com\/menu","open24_hours":null,"waitlist_reservation":null},"price":"$$"}
{"id":"rsL24bMloQTxJbZHwzIhtA","alias":"the-melt-sunnyvale-2","name":"The Melt","image_url":"https:\/\/s3-media2.fl.yelpcdn.com\/bphoto\/96iHSamgeMk-HKFgrnmF6A\/o.jpg","is_closed":false,"url":"https:\/\/www.yelp.com\/biz\/the-melt-sunnyvale-2?adjust_creative=wNVJ2NQ-VXEtJk4AjWcSCg&utm_campaign=yelp_api_v3&utm_medium=api_v3_business_search&utm_source=wNVJ2NQ-VXEtJk4AjWcSCg","review_count":170,"categories":[{"alias":"sandwiches","title":"Sandwiches"},{"alias":"burgers","title":"Burgers"},{"alias":"chickenshop","title":"Chicken Shop"}],"rating":4.6,"coordinates":{"latitude":37.374971,"longitude":-122.033517},"transactions":["delivery","pickup"],"location":{"address1":"301 W McKinley Ave","address2":"Ste 120","address3":null,"city":"Sunnyvale","zip_code":"94086","country":"US","state":"CA","display_address":["301 W McKinley Ave","Ste 120","Sunnyvale, CA 94086"]},"phone":"+14083242942","display_phone":"(408) 324-2942","distance":817.9235917541,"business_hours":[{"open":[{"is_overnight":false,"start":"1000","end":"0000","day":0},{"is_overnight":false,"start":"1000","end":"0000","day":1},{"is_overnight":false,"start":"1000","end":"0000","day":2},{"is_overnight":true,"start":"1000","end":"0100","day":3},{"is_overnight":true,"start":"1000","end":"0100","day":4},{"is_overnight":true,"start":"1000","end":"0100","day":5},{"is_overnight":false,"start":"1000","end":"0000","day":6}],"hours_type":"REGULAR","is_open_now":true}],"attributes":{"business_temp_closed":null,"menu_url":"https:\/\/www.themelt.com\/our-menu","open24_hours":null,"waitlist_reservation":null},"price":"$$"}
{"id":"5LqUuxSANuoErm7L1Uznew","alias":"craft-house-sunnyvale-6","name":"Craft House","image_url":"https:\/\/s3-media2.fl.yelpcdn.com\/bphoto\/Cx3e1jItVH1lSImRuFiG0Q\/o.jpg","is_closed":false,"url":"https:\/\/www.yelp.com\/biz\/craft-house-sunnyvale-6?adjust_creative=wNVJ2NQ-VXEtJk4AjWcSCg&utm_campaign=yelp_api_v3&utm_medium=api_v3_business_search&utm_source=wNVJ2NQ-VXEtJk4AjWcSCg","review_count":49,"categories":[{"alias":"bars","title":"Bars"},{"alias":"tradamerican","title":"American"},{"alias":"beer_and_wine","title":"Beer, Wine & Spirits"}],"rating":4.6,"coordinates":{"latitude":37.3758,"longitude":-122.02842},"transactions":[],"location":{"address1":"295 E Washington Ave","address2":"","address3":null,"city":"Sunnyvale","zip_code":"94086","country":"US","state":"CA","display_address":["295 E Washington Ave","Sunnyvale, CA 94086"]},"phone":"+14086387822","display_phone":"(408) 638-7822","distance":412.3434464363,"business_hours":[{"open":[{"is_overnight":true,"start":"1400","end":"0200","day":0},{"is_overnight":true,"start":"1400","end":"0200","day":1},{"is_overnight":true,"start":"1400","end":"0200","day":2},{"is_overnight":true,"start":"1400","end":"0200","day":3},{"is_overnight":true,"start":"1400","end":"0200","day":4},{"is_overnight":true,"start":"1400","end":"0200","day":5},{"is_overnight":true,"start":"1000","end":"0200","day":6}],"hours_type":"REGULAR","is_open_now":true}],"attributes":{"business_temp_closed":null,"menu_url":null,"open24_hours":null,"waitlist_reservation":null},"price":null}
{"id":"-CQXDEjeg-1PD2ue-pu1ww","alias":"nahita-bakery-sunnyvale","name":"Nahita Bakery","image_url":"https:\/\/s3-media1.fl.yelpcdn.com\/bphoto\/_tzfQGMW4hcejFGD1-Jc6Q\/o.jpg","is_closed":false,"url":"https:\/\/www.yelp.com\/biz\/nahita-bakery-sunnyvale?adjust_creative=wNVJ2NQ-VXEtJk4AjWcSCg&utm_campaign=yelp_api_v3&utm_medium=api_v3_business_search&utm_source=wNVJ2NQ-VXEtJk4AjWcSCg","review_count":67,"categories":[{"alias":"bakeries","title":"Bakeries"},{"alias":"mediterranean","title":"Mediterranean"},{"alias":"breakfast_brunch","title":"Breakfast & Brunch"}],"rating":4.6,"coordinates":{"latitude":37.3507073141,"longitude":-122.0492938938},"transactions":["delivery","pickup"],"location":{"address1":"1334 S Mary Ave","address2":null,"address3":"","city":"Sunnyvale","zip_code":"94087","country":"US","state":"CA","display_address":["1334 S Mary Ave","Sunnyvale, CA 94087"]},"phone":"+14084208982","display_phone":"(408) 420-8982","distance":3392.0137740706,"business_hours":[{"open":[{"is_overnight":false,"start":"0830","end":"2030","day":0},{"is_overnight":false,"start":"0830","end":"2030","day":1},{"is_overnight":false,"start":"0830","end":"2030","day":2},{"is_overnight":false,"start":"0830","end":"2030","day":3},{"is_overnight":false,"start":"0830","end":"2030","day":4},{"is_overnight":false,"start":"0830","end":"2030","day":5},{"is_overnight":false,"start":"0830","end":"2030","day":6}],"hours_type":"REGULAR","is_open_now":false}],"attributes":{"business_temp_closed":null,"menu_url":"https:\/\/www.nahita.shop\/s\/order?location=11ee743b1376c571877e3cecef6d615a#most-popular","open24_hours":null,"waitlist_reservation":null},"price":null}
